phytest/__init__.py
phytest/bio/__init__.py
phytest/bio/alignment.py
phytest/bio/data.py
phytest/bio/sequence.py
phytest/bio/tree.py
phytest/cli.py
phytest/main.py
phytest/report/logo.css
phytest/utils.py
phytest-1.4.1.dist-info/LICENSE
phytest-1.4.1.dist-info/METADATA
phytest-1.4.1.dist-info/WHEEL
phytest-1.4.1.dist-info/entry_points.txt
phytest-1.4.1.dist-info/RECORD
