Metadata-Version: 2.1
Name: phytest
Version: 1.4.1
Summary: Quality control for phylogenetic pipelines using pytest
Author: Wytamma Wirth
Author-email: wytamma.wirth@me.com
Requires-Python: >=3.8,<3.12
Classifier: Framework :: Pytest
Classifier: Programming Language :: Python :: 3
Classifier: Programming Language :: Python :: 3.8
Classifier: Programming Language :: Python :: 3.9
Classifier: Programming Language :: Python :: 3.10
Classifier: Programming Language :: Python :: 3.11
Requires-Dist: biopython (>=1.79)
Requires-Dist: numpy (>=1.22.3)
Requires-Dist: phylo-treetime (>=0.8.6)
Requires-Dist: pytest (>=7.1.1)
Requires-Dist: pytest-html (>=3.1.1)
Requires-Dist: pytest-sugar (>=0.9.4)
Requires-Dist: pytest-xdist (>=3.2.0)
Requires-Dist: scipy (>=1.8.0)
Requires-Dist: typer (>=0.4.1)
